molviewspec/__init__.py
molviewspec/builder.py
molviewspec/molstar_widgets.py
molviewspec/mvsx_converter.py
molviewspec/nodes.py
molviewspec/utils.py
molviewspec-1.8.1.dist-info/licenses/LICENSE.txt
molviewspec-1.8.1.dist-info/METADATA
molviewspec-1.8.1.dist-info/WHEEL
molviewspec-1.8.1.dist-info/top_level.txt
molviewspec-1.8.1.dist-info/RECORD
