Metadata-Version: 2.4
Name: molviewspec
Version: 1.8.1
Summary: Generate Mol* views using this simple Python library, which allows you to compose complex scenes in a step-wise manner.
Home-page: https://github.com/molstar/mol-view-spec
Download-URL: https://github.com/molstar/mol-view-spec/archive/v1.8.1.tar.gz
Author: Sebastian Bittrich, Adam Midlik, David Sehnal
Author-email: sebastian.bittrich@rcsb.org, midlik@ebi.ac.uk, david.sehnal@gmail.com
License: MIT
Keywords: molecular graphics,scientific visualization,web graphics,view specification,scene building,Mol*
Classifier: Development Status :: 3 - Alpha
Classifier: Intended Audience :: Science/Research
Classifier: Topic :: Software Development :: Build Tools
Classifier: License :: OSI Approved :: MIT License
Classifier: Programming Language :: Python
Classifier: Programming Language :: Python :: 3
Classifier: Programming Language :: Python :: 3.10
Classifier: Topic :: Scientific/Engineering :: Bio-Informatics
Classifier: Natural Language :: English
Classifier: Typing :: Typed
License-File: LICENSE.txt
Requires-Dist: pydantic<3,>=1
Dynamic: author
Dynamic: author-email
Dynamic: classifier
Dynamic: description
Dynamic: description-content-type
Dynamic: download-url
Dynamic: home-page
Dynamic: keywords
Dynamic: license
Dynamic: license-file
Dynamic: requires-dist
Dynamic: summary
